ansel/__init__.py
ansel/ansel.py
ansel/codec.py
ansel/incremental.py
ansel/encodings/__init__.py
ansel/encodings/ansel.py
ansel/encodings/gedcom.py
ansel-0.2.0.dist-info/AUTHORS.rst
ansel-0.2.0.dist-info/LICENSE
ansel-0.2.0.dist-info/METADATA
ansel-0.2.0.dist-info/WHEEL
ansel-0.2.0.dist-info/top_level.txt
ansel-0.2.0.dist-info/zip-safe
ansel-0.2.0.dist-info/RECORD
