Metadata-Version: 2.1
Name: ansel
Version: 0.2.0
Summary: Codecs for reading/writing documents in the ANSEL character set.
Home-page: https://github.com/haney/python-ansel
Author: David Haney
Author-email: david.haney@gmail.com
License: MIT license
Keywords: ansel gedcom
Platform: UNKNOWN
Classifier: Development Status :: 3 - Alpha
Classifier: Intended Audience :: Developers
Classifier: License :: OSI Approved :: MIT License
Classifier: Natural Language :: English
Classifier: Programming Language :: Python :: 3
Classifier: Programming Language :: Python :: 3.6
Classifier: Programming Language :: Python :: 3.7
Classifier: Programming Language :: Python :: 3.8
Classifier: Programming Language :: Python :: 3.9
Classifier: Programming Language :: Python :: Implementation :: CPython
